attridict.py
mixins.py
tests.py
attridict-0.0.9.dist-info/LICENSE
attridict-0.0.9.dist-info/METADATA
attridict-0.0.9.dist-info/WHEEL
attridict-0.0.9.dist-info/top_level.txt
attridict-0.0.9.dist-info/RECORD
