Metadata-Version: 2.1
Name: attridict
Version: 0.0.9
Summary: A dict implementation with support for easy and clean access of its values through attributes
Home-page: https://github.com/alvinshaita/attridict
Author: Alvin Shaita
Author-email: alvinshaita@gmail.com
License: MIT License
Keywords: attridict,attrdict,struct,dict,dot,attribute,attributes,dictionary,attr,object
Classifier: Intended Audience :: Developers
Classifier: License :: OSI Approved :: MIT License
Classifier: Programming Language :: Python :: 3
Classifier: Programming Language :: Python :: Implementation :: CPython
Classifier: Programming Language :: Python :: Implementation :: PyPy
License-File: LICENSE
Requires-Dist: PyYAML ==6.0.1
